odc/__init__.py
odc/analysis.py
odc/census_mx.py
odc/data.py
odc/network_analysis.py
odc/raster.py
odc/settings.py
odc/utils.py
odc/visualization.py
odc-0.1.3.dist-info/METADATA
odc-0.1.3.dist-info/WHEEL
odc-0.1.3.dist-info/RECORD
